puaa/app.py
puaa/puaa.py
puaa-0.3.2.dist-info/LICENSE.txt
puaa-0.3.2.dist-info/METADATA
puaa-0.3.2.dist-info/WHEEL
puaa-0.3.2.dist-info/top_level.txt
puaa-0.3.2.dist-info/RECORD
