Metadata-Version: 2.1
Name: puaa
Version: 0.3.2
Summary: Python UAA test server
Home-page: https://gitlab.com/romk/puaa
Author: romk
Author-email: r0mk@gmx.net
License: MIT
Platform: UNKNOWN
Classifier: Development Status :: 3 - Alpha
Classifier: Intended Audience :: Developers
Classifier: Topic :: Software Development :: Testing :: Mocking
Classifier: License :: OSI Approved :: MIT License
Classifier: Programming Language :: Python :: 3
Requires-Python: >=3
Requires-Dist: Authlib
Requires-Dist: cryptography
Requires-Dist: Flask
Requires-Dist: gunicorn[gevent]
Requires-Dist: PyYAML (>=3.12)
